{
  "selections": {
    "mode": "SIMPLE"
  },
  "placements": {},
  "schematic_projects_manager": {},
  "operation_mode": "PASTE_SCHEMATIC",
  "render_range": {
    "mode": "ALL",
    "axis": "y",
    "layer_single": 181,
    "layer_above": 243,
    "layer_below": 176,
    "layer_range_min": 0,
    "layer_range_max": 0,
    "hotkey_range_min": false,
    "hotkey_range_max": false
  },
  "area_simple": {
    "name": "Unnamed",
    "current": "Unnamed",
    "boxes": [
      {
        "pos1": [
          105,
          127,
          -322
        ],
        "pos2": [
          105,
          127,
          -322
        ],
        "name": "Unnamed"
      }
    ]
  },
  "tool_mode_data": {
    "delete": {
      "use_placement": false
    }
  },
  "block_entities": {}
}